pandas-express/__init__.py
pandas_express/__init__.py
pandas_express-0.0.8.dist-info/METADATA
pandas_express-0.0.8.dist-info/WHEEL
pandas_express-0.0.8.dist-info/top_level.txt
pandas_express-0.0.8.dist-info/RECORD
