Metadata-Version: 2.1
Name: pandas-express
Version: 0.0.8
Summary: A collection of Data Science helper functions
Home-page: https://lambdaschool.com/courses/data-science/
Author: spentaur
License: UNKNOWN
Platform: UNKNOWN
Classifier: Programming Language :: Python :: 3
Classifier: License :: OSI Approved :: MIT License
Classifier: Operating System :: OS Independent
Requires-Python: >=3.5
Requires-Dist: pandas
Requires-Dist: pandas-flavor
Requires-Dist: pyspellchecker
